/*     */ package it.unimi.dsi.fastutil.doubles;
/*     */ 
/*     */ import it.unimi.dsi.fastutil.BigArrays;
/*     */ import it.unimi.dsi.fastutil.BigList;
/*     */ import it.unimi.dsi.fastutil.BigListIterator;
/*     */ import it.unimi.dsi.fastutil.HashCommon;
/*     */ import java.io.Serializable;
/*     */ import java.util.Collection;
/*     */ import java.util.Iterator;
/*     */ import java.util.NoSuchElementException;
/*     */ import java.util.Objects;
/*     */ import java.util.RandomAccess;
/*     */ import java.util.Spliterator;
/*     */ import java.util.function.DoubleConsumer;
/*     */ 
/*     */ 
/*     */ 
/*     */ 
/*     */ 
/*     */ 
/*     */ 
/*     */ 
/*     */ 
/*     */ 
/*     */ 
/*     */ 
/*     */ 
/*     */ 
/*     */ 
/*     */ 
/*     */ 
/*     */ 
/*     */ 
/*     */ 
/*     */ 
/*     */ 
/*     */ 
/*     */ 
/*     */ 
/*     */ 
/*     */ 
/*     */ 
/*     */ 
/*     */ 
/*     */ 
/*     */ public abstract class AbstractDoubleBigList
/*     */   extends AbstractDoubleCollection
/*     */   implements DoubleBigList, DoubleStack
/*     */ {
/*     */   protected void ensureIndex(long index) {
/*  51 */     if (index < 0L) throw new IndexOutOfBoundsException("Index (" + index + ") is negative"); 
/*  52 */     if (index > size64()) throw new IndexOutOfBoundsException("Index (" + index + ") is greater than list size (" + size64() + ")");
/*     */   
/*     */   }
/*     */ 
/*     */ 
/*     */ 
/*     */ 
/*     */ 
/*     */ 
/*     */   
/*     */   protected void ensureRestrictedIndex(long index) {
/*  63 */     if (index < 0L) throw new IndexOutOfBoundsException("Index (" + index + ") is negative"); 
/*  64 */     if (index >= size64()) throw new IndexOutOfBoundsException("Index (" + index + ") is greater than or equal to list size (" + size64() + ")");
/*     */   
/*     */   }
/*     */ 
/*     */ 
/*     */ 
/*     */ 
/*     */ 
/*     */   
/*     */   public void add(long index, double k) {
/*  74 */     throw new UnsupportedOperationException();
/*     */   }
/*     */ 
/*     */ 
/*     */ 
/*     */ 
/*     */ 
/*     */ 
/*     */ 
/*     */   
/*     */   public boolean add(double k) {
/*  85 */     add(size64(), k);
/*  86 */     return true;
/*     */   }
/*     */ 
/*     */ 
/*     */ 
/*     */ 
/*     */ 
/*     */ 
/*     */   
/*     */   public double removeDouble(long i) {
/*  96 */     throw new UnsupportedOperationException();
/*     */   }
/*     */ 
/*     */ 
/*     */ 
/*     */ 
/*     */ 
/*     */ 
/*     */   
/*     */   public double set(long index, double k) {
/* 106 */     throw new UnsupportedOperationException();
/*     */   }
/*     */ 
/*     */ 
/*     */ 
/*     */ 
/*     */ 
/*     */ 
/*     */ 
/*     */   
/*     */   public boolean addAll(long index, Collection<? extends Double> c) {
/*     */     // Byte code:
/*     */     //   0: aload_0
/*     */     //   1: lload_1
/*     */     //   2: invokevirtual ensureIndex : (J)V
/*     */     //   5: aload_3
/*     */     //   6: invokeinterface iterator : ()Ljava/util/Iterator;
/*     */     //   11: astore #4
/*     */     //   13: aload #4
/*     */     //   15: invokeinterface hasNext : ()Z
/*     */     //   20: istore #5
/*     */     //   22: aload #4
/*     */     //   24: invokeinterface hasNext : ()Z
/*     */     //   29: ifeq -> 54
/*     */     //   32: aload_0
/*     */     //   33: lload_1
/*     */     //   34: dup2
/*     */     //   35: lconst_1
/*     */     //   36: ladd
/*     */     //   37: lstore_1
/*     */     //   38: aload #4
/*     */     //   40: invokeinterface next : ()Ljava/lang/Object;
/*     */     //   45: checkcast java/lang/Double
/*     */     //   48: invokevirtual add : (JLjava/lang/Double;)V
/*     */     //   51: goto -> 22
/*     */     //   54: iload #5
/*     */     //   56: ireturn
/*     */     // Line number table:
/*     */     //   Java source line number -> byte code offset
/*     */     //   #112	-> 0
/*     */     //   #113	-> 5
/*     */     //   #114	-> 13
/*     */     //   #115	-> 22
/*     */     //   #116	-> 54
/*     */     // Local variable table:
/*     */     //   start	length	slot	name	descriptor
/*     */     //   0	57	0	this	Lit/unimi/dsi/fastutil/doubles/AbstractDoubleBigList;
/*     */     //   0	57	1	index	J
/*     */     //   0	57	3	c	Ljava/util/Collection;
/*     */     //   13	44	4	i	Ljava/util/Iterator;
/*     */     //   22	35	5	retVal	Z
/*     */     // Local variable type table:
/*     */     //   start	length	slot	name	signature
/*     */     //   0	57	3	c	Ljava/util/Collection<+Ljava/lang/Double;>;
/*     */     //   13	44	4	i	Ljava/util/Iterator<+Ljava/lang/Double;>;
/*     */   }
/*     */ 
/*     */ 
/*     */ 
/*     */ 
/*     */ 
/*     */ 
/*     */   
/*     */   public boolean addAll(Collection<? extends Double> c) {
/* 127 */     return addAll(size64(), c);
/*     */   }
/*     */ 
/*     */ 
/*     */ 
/*     */ 
/*     */ 
/*     */ 
/*     */   
/*     */   public DoubleBigListIterator iterator() {
/* 137 */     return listIterator();
/*     */   }
/*     */ 
/*     */ 
/*     */ 
/*     */ 
/*     */ 
/*     */ 
/*     */   
/*     */   public DoubleBigListIterator listIterator() {
/* 147 */     return listIterator(0L);
/*     */   }
/*     */ 
/*     */ 
/*     */ 
/*     */ 
/*     */ 
/*     */ 
/*     */   
/*     */   public DoubleBigListIterator listIterator(long index) {
/* 157 */     ensureIndex(index);
/* 158 */     return new DoubleBigListIterators.AbstractIndexBasedBigListIterator(0L, index)
/*     */       {
/*     */         protected final double get(long i) {
/* 161 */           return AbstractDoubleBigList.this.getDouble(i);
/*     */         }
/*     */ 
/*     */         
/*     */         protected final void add(long i, double k) {
/* 166 */           AbstractDoubleBigList.this.add(i, k);
/*     */         }
/*     */ 
/*     */         
/*     */         protected final void set(long i, double k) {
/* 171 */           AbstractDoubleBigList.this.set(i, k);
/*     */         }
/*     */ 
/*     */         
/*     */         protected final void remove(long i) {
/* 176 */           AbstractDoubleBigList.this.removeDouble(i);
/*     */         }
/*     */ 
/*     */         
/*     */         protected final long getMaxPos() {
/* 181 */           return AbstractDoubleBigList.this.size64();
/*     */         }
/*     */       };
/*     */   }
/*     */   
/*     */   static final class IndexBasedSpliterator extends DoubleBigSpliterators.LateBindingSizeIndexBasedSpliterator {
/*     */     final DoubleBigList l;
/*     */     
/*     */     IndexBasedSpliterator(DoubleBigList l, long pos) {
/* 190 */       super(pos);
/* 191 */       this.l = l;
/*     */     }
/*     */     
/*     */     IndexBasedSpliterator(DoubleBigList l, long pos, long maxPos) {
/* 195 */       super(pos, maxPos);
/* 196 */       this.l = l;
/*     */     }
/*     */ 
/*     */     
/*     */     protected final long getMaxPosFromBackingStore() {
/* 201 */       return this.l.size64();
/*     */     }
/*     */ 
/*     */     
/*     */     protected final double get(long i) {
/* 206 */       return this.l.getDouble(i);
/*     */     }
/*     */ 
/*     */     
/*     */     protected final IndexBasedSpliterator makeForSplit(long pos, long maxPos) {
/* 211 */       return new IndexBasedSpliterator(this.l, pos, maxPos);
/*     */     }
/*     */   }
/*     */ 
/*     */ 
/*     */ 
/*     */ 
/*     */ 
/*     */ 
/*     */ 
/*     */   
/*     */   public boolean contains(double k) {
/* 223 */     return (indexOf(k) >= 0L);
/*     */   }
/*     */ 
/*     */   
/*     */   public long indexOf(double k) {
/* 228 */     DoubleBigListIterator i = listIterator();
/*     */     
/* 230 */     while (i.hasNext()) {
/* 231 */       double e = i.nextDouble();
/* 232 */       if (Double.doubleToLongBits(k) == Double.doubleToLongBits(e)) return i.previousIndex(); 
/*     */     } 
/* 234 */     return -1L;
/*     */   }
/*     */ 
/*     */   
/*     */   public long lastIndexOf(double k) {
/* 239 */     DoubleBigListIterator i = listIterator(size64());
/*     */     
/* 241 */     while (i.hasPrevious()) {
/* 242 */       double e = i.previousDouble();
/* 243 */       if (Double.doubleToLongBits(k) == Double.doubleToLongBits(e)) return i.nextIndex(); 
/*     */     } 
/* 245 */     return -1L;
/*     */   }
/*     */ 
/*     */   
/*     */   public void size(long size) {
/* 250 */     long i = size64();
/* 251 */     if (size > i) { for (; i++ < size; add(0.0D)); }
/* 252 */     else { for (; i-- != size; remove(i)); }
/*     */   
/*     */   }
/*     */   
/*     */   public DoubleBigList subList(long from, long to) {
/* 257 */     ensureIndex(from);
/* 258 */     ensureIndex(to);
/* 259 */     if (from > to) throw new IndexOutOfBoundsException("Start index (" + from + ") is greater than end index (" + to + ")"); 
/* 260 */     return (this instanceof RandomAccess) ? new DoubleRandomAccessSubList(this, from, to) : new DoubleSubList(this, from, to);
/*     */   }
/*     */ 
/*     */ 
/*     */ 
/*     */ 
/*     */ 
/*     */ 
/*     */ 
/*     */ 
/*     */   
/*     */   public void forEach(DoubleConsumer action) {
/* 272 */     if (this instanceof RandomAccess) {
/* 273 */       for (long i = 0L, max = size64(); i < max; i++) {
/* 274 */         action.accept(getDouble(i));
/*     */       }
/*     */     } else {
/* 277 */       super.forEach(action);
/*     */     } 
/*     */   }
/*     */ 
/*     */ 
/*     */ 
/*     */ 
/*     */ 
/*     */ 
/*     */ 
/*     */ 
/*     */   
/*     */   public void removeElements(long from, long to) {
/* 290 */     ensureIndex(to);
/* 291 */     DoubleBigListIterator i = listIterator(from);
/* 292 */     long n = to - from;
/* 293 */     if (n < 0L) throw new IllegalArgumentException("Start index (" + from + ") is greater than end index (" + to + ")"); 
/* 294 */     while (n-- != 0L) {
/* 295 */       i.nextDouble();
/* 296 */       i.remove();
/*     */     } 
/*     */   }
/*     */ 
/*     */ 
/*     */ 
/*     */ 
/*     */ 
/*     */ 
/*     */ 
/*     */ 
/*     */ 
/*     */ 
/*     */ 
/*     */   
/*     */   public void addElements(long index, double[][] a, long offset, long length) {
/*     */     // Byte code:
/*     */     //   0: aload_0
/*     */     //   1: lload_1
/*     */     //   2: invokevirtual ensureIndex : (J)V
/*     */     //   5: aload_3
/*     */     //   6: lload #4
/*     */     //   8: lload #6
/*     */     //   10: invokestatic ensureOffsetLength : ([[DJJ)V
/*     */     //   13: aload_0
/*     */     //   14: instanceof java/util/RandomAccess
/*     */     //   17: ifeq -> 55
/*     */     //   20: lload #6
/*     */     //   22: dup2
/*     */     //   23: lconst_1
/*     */     //   24: lsub
/*     */     //   25: lstore #6
/*     */     //   27: lconst_0
/*     */     //   28: lcmp
/*     */     //   29: ifeq -> 95
/*     */     //   32: aload_0
/*     */     //   33: lload_1
/*     */     //   34: dup2
/*     */     //   35: lconst_1
/*     */     //   36: ladd
/*     */     //   37: lstore_1
/*     */     //   38: aload_3
/*     */     //   39: lload #4
/*     */     //   41: dup2
/*     */     //   42: lconst_1
/*     */     //   43: ladd
/*     */     //   44: lstore #4
/*     */     //   46: invokestatic get : ([[DJ)D
/*     */     //   49: invokevirtual add : (JD)V
/*     */     //   52: goto -> 20
/*     */     //   55: aload_0
/*     */     //   56: lload_1
/*     */     //   57: invokevirtual listIterator : (J)Lit/unimi/dsi/fastutil/doubles/DoubleBigListIterator;
/*     */     //   60: astore #8
/*     */     //   62: lload #6
/*     */     //   64: dup2
/*     */     //   65: lconst_1
/*     */     //   66: lsub
/*     */     //   67: lstore #6
/*     */     //   69: lconst_0
/*     */     //   70: lcmp
/*     */     //   71: ifeq -> 95
/*     */     //   74: aload #8
/*     */     //   76: aload_3
/*     */     //   77: lload #4
/*     */     //   79: dup2
/*     */     //   80: lconst_1
/*     */     //   81: ladd
/*     */     //   82: lstore #4
/*     */     //   84: invokestatic get : ([[DJ)D
/*     */     //   87: invokeinterface add : (D)V
/*     */     //   92: goto -> 62
/*     */     //   95: return
/*     */     // Line number table:
/*     */     //   Java source line number -> byte code offset
/*     */     //   #309	-> 0
/*     */     //   #310	-> 5
/*     */     //   #311	-> 13
/*     */     //   #312	-> 20
/*     */     //   #314	-> 55
/*     */     //   #315	-> 62
/*     */     //   #317	-> 95
/*     */     // Local variable table:
/*     */     //   start	length	slot	name	descriptor
/*     */     //   62	33	8	iter	Lit/unimi/dsi/fastutil/doubles/DoubleBigListIterator;
/*     */     //   0	96	0	this	Lit/unimi/dsi/fastutil/doubles/AbstractDoubleBigList;
/*     */     //   0	96	1	index	J
/*     */     //   0	96	3	a	[[D
/*     */     //   0	96	4	offset	J
/*     */     //   0	96	6	length	J
/*     */   }
/*     */ 
/*     */ 
/*     */ 
/*     */ 
/*     */ 
/*     */ 
/*     */ 
/*     */ 
/*     */ 
/*     */ 
/*     */   
/*     */   public void addElements(long index, double[][] a) {
/* 326 */     addElements(index, a, 0L, BigArrays.length(a));
/*     */   }
/*     */ 
/*     */ 
/*     */ 
/*     */ 
/*     */ 
/*     */ 
/*     */ 
/*     */ 
/*     */ 
/*     */   
/*     */   public void getElements(long from, double[][] a, long offset, long length) {
/*     */     // Byte code:
/*     */     //   0: aload_0
/*     */     //   1: lload_1
/*     */     //   2: invokevirtual ensureIndex : (J)V
/*     */     //   5: aload_3
/*     */     //   6: lload #4
/*     */     //   8: lload #6
/*     */     //   10: invokestatic ensureOffsetLength : ([[DJJ)V
/*     */     //   13: lload_1
/*     */     //   14: lload #6
/*     */     //   16: ladd
/*     */     //   17: aload_0
/*     */     //   18: invokevirtual size64 : ()J
/*     */     //   21: lcmp
/*     */     //   22: ifle -> 72
/*     */     //   25: new java/lang/IndexOutOfBoundsException
/*     */     //   28: dup
/*     */     //   29: new java/lang/StringBuilder
/*     */     //   32: dup
/*     */     //   33: invokespecial <init> : ()V
/*     */     //   36: ldc 'End index ('
/*     */     //   38: invokevirtual append : (Ljava/lang/String;)Ljava/lang/StringBuilder;
/*     */     //   41: lload_1
/*     */     //   42: lload #6
/*     */     //   44: ladd
/*     */     //   45: invokevirtual append : (J)Ljava/lang/StringBuilder;
/*     */     //   48: ldc ') is greater than list size ('
/*     */     //   50: invokevirtual append : (Ljava/lang/String;)Ljava/lang/StringBuilder;
/*     */     //   53: aload_0
/*     */     //   54: invokevirtual size64 : ()J
/*     */     //   57: invokevirtual append : (J)Ljava/lang/StringBuilder;
/*     */     //   60: ldc ')'
/*     */     //   62: invokevirtual append : (Ljava/lang/String;)Ljava/lang/StringBuilder;
/*     */     //   65: invokevirtual toString : ()Ljava/lang/String;
/*     */     //   68: invokespecial <init> : (Ljava/lang/String;)V
/*     */     //   71: athrow
/*     */     //   72: aload_0
/*     */     //   73: instanceof java/util/RandomAccess
/*     */     //   76: ifeq -> 122
/*     */     //   79: lload_1
/*     */     //   80: lstore #8
/*     */     //   82: lload #6
/*     */     //   84: dup2
/*     */     //   85: lconst_1
/*     */     //   86: lsub
/*     */     //   87: lstore #6
/*     */     //   89: lconst_0
/*     */     //   90: lcmp
/*     */     //   91: ifeq -> 119
/*     */     //   94: aload_3
/*     */     //   95: lload #4
/*     */     //   97: dup2
/*     */     //   98: lconst_1
/*     */     //   99: ladd
/*     */     //   100: lstore #4
/*     */     //   102: aload_0
/*     */     //   103: lload #8
/*     */     //   105: dup2
/*     */     //   106: lconst_1
/*     */     //   107: ladd
/*     */     //   108: lstore #8
/*     */     //   110: invokevirtual getDouble : (J)D
/*     */     //   113: invokestatic set : ([[DJD)V
/*     */     //   116: goto -> 82
/*     */     //   119: goto -> 162
/*     */     //   122: aload_0
/*     */     //   123: lload_1
/*     */     //   124: invokevirtual listIterator : (J)Lit/unimi/dsi/fastutil/doubles/DoubleBigListIterator;
/*     */     //   127: astore #8
/*     */     //   129: lload #6
/*     */     //   131: dup2
/*     */     //   132: lconst_1
/*     */     //   133: lsub
/*     */     //   134: lstore #6
/*     */     //   136: lconst_0
/*     */     //   137: lcmp
/*     */     //   138: ifeq -> 162
/*     */     //   141: aload_3
/*     */     //   142: lload #4
/*     */     //   144: dup2
/*     */     //   145: lconst_1
/*     */     //   146: ladd
/*     */     //   147: lstore #4
/*     */     //   149: aload #8
/*     */     //   151: invokeinterface nextDouble : ()D
/*     */     //   156: invokestatic set : ([[DJD)V
/*     */     //   159: goto -> 129
/*     */     //   162: return
/*     */     // Line number table:
/*     */     //   Java source line number -> byte code offset
/*     */     //   #338	-> 0
/*     */     //   #339	-> 5
/*     */     //   #340	-> 13
/*     */     //   #341	-> 72
/*     */     //   #342	-> 79
/*     */     //   #343	-> 82
/*     */     //   #344	-> 119
/*     */     //   #345	-> 122
/*     */     //   #346	-> 129
/*     */     //   #348	-> 162
/*     */     // Local variable table:
/*     */     //   start	length	slot	name	descriptor
/*     */     //   82	37	8	current	J
/*     */     //   129	33	8	i	Lit/unimi/dsi/fastutil/doubles/DoubleBigListIterator;
/*     */     //   0	163	0	this	Lit/unimi/dsi/fastutil/doubles/AbstractDoubleBigList;
/*     */     //   0	163	1	from	J
/*     */     //   0	163	3	a	[[D
/*     */     //   0	163	4	offset	J
/*     */     //   0	163	6	length	J
/*     */   }
/*     */ 
/*     */ 
/*     */ 
/*     */ 
/*     */ 
/*     */ 
/*     */ 
/*     */ 
/*     */ 
/*     */   
/*     */   public void setElements(long index, double[][] a, long offset, long length) {
/* 352 */     ensureIndex(index);
/* 353 */     BigArrays.ensureOffsetLength(a, offset, length);
/* 354 */     if (index + length > size64()) throw new IndexOutOfBoundsException("End index (" + (index + length) + ") is greater than list size (" + size64() + ")"); 
/* 355 */     if (this instanceof RandomAccess) {
/* 356 */       long i; for (i = 0L; i < length; i++) {
/* 357 */         set(i + index, BigArrays.get(a, i + offset));
/*     */       }
/*     */     } else {
/* 360 */       DoubleBigListIterator iter = listIterator(index);
/* 361 */       long i = 0L;
/* 362 */       while (i < length) {
/* 363 */         iter.nextDouble();
/* 364 */         iter.set(BigArrays.get(a, offset + i++));
/*     */       } 
/*     */     } 
/*     */   }
/*     */ 
/*     */ 
/*     */ 
/*     */ 
/*     */ 
/*     */ 
/*     */   
/*     */   public void clear() {
/* 376 */     removeElements(0L, size64());
/*     */   }
/*     */ 
/*     */ 
/*     */ 
/*     */ 
/*     */ 
/*     */ 
/*     */ 
/*     */   
/*     */   @Deprecated
/*     */   public int size() {
/* 388 */     return (int)Math.min(2147483647L, size64());
/*     */   }
/*     */ 
/*     */ 
/*     */ 
/*     */ 
/*     */ 
/*     */ 
/*     */   
/*     */   public int hashCode() {
/* 398 */     DoubleIterator i = iterator();
/* 399 */     int h = 1;
/* 400 */     long s = size64();
/* 401 */     while (s-- != 0L) {
/* 402 */       double k = i.nextDouble();
/* 403 */       h = 31 * h + HashCommon.double2int(k);
/*     */     } 
/* 405 */     return h;
/*     */   }
/*     */ 
/*     */   
/*     */   public boolean equals(Object o) {
/* 410 */     if (o == this) return true; 
/* 411 */     if (!(o instanceof BigList)) return false; 
/* 412 */     BigList<?> l = (BigList)o;
/* 413 */     long s = size64();
/* 414 */     if (s != l.size64()) return false; 
/* 415 */     if (l instanceof DoubleBigList) {
/* 416 */       DoubleBigListIterator doubleBigListIterator1 = listIterator(), doubleBigListIterator2 = ((DoubleBigList)l).listIterator();
/* 417 */       while (s-- != 0L) { if (doubleBigListIterator1.nextDouble() != doubleBigListIterator2.nextDouble()) return false;  }
/* 418 */        return true;
/*     */     } 
/* 420 */     BigListIterator<?> i1 = listIterator(), i2 = l.listIterator();
/* 421 */     while (s-- != 0L) { if (!Objects.equals(i1.next(), i2.next())) return false;  }
/* 422 */      return true;
/*     */   }
/*     */ 
/*     */ 
/*     */ 
/*     */ 
/*     */ 
/*     */ 
/*     */ 
/*     */ 
/*     */ 
/*     */ 
/*     */ 
/*     */   
/*     */   public int compareTo(BigList<? extends Double> l) {
/* 437 */     if (l == this) return 0; 
/* 438 */     if (l instanceof DoubleBigList) {
/* 439 */       DoubleBigListIterator doubleBigListIterator1 = listIterator(), doubleBigListIterator2 = ((DoubleBigList)l).listIterator();
/*     */ 
/*     */       
/* 442 */       while (doubleBigListIterator1.hasNext() && doubleBigListIterator2.hasNext()) {
/* 443 */         double e1 = doubleBigListIterator1.nextDouble();
/* 444 */         double e2 = doubleBigListIterator2.nextDouble(); int r;
/* 445 */         if ((r = Double.compare(e1, e2)) != 0) return r; 
/*     */       } 
/* 447 */       return doubleBigListIterator2.hasNext() ? -1 : (doubleBigListIterator1.hasNext() ? 1 : 0);
/*     */     } 
/* 449 */     BigListIterator<? extends Double> i1 = listIterator(), i2 = l.listIterator();
/*     */     
/* 451 */     while (i1.hasNext() && i2.hasNext()) {
/* 452 */       int r; if ((r = ((Comparable<Object>)i1.next()).compareTo(i2.next())) != 0) return r; 
/*     */     } 
/* 454 */     return i2.hasNext() ? -1 : (i1.hasNext() ? 1 : 0);
/*     */   }
/*     */ 
/*     */   
/*     */   public void push(double o) {
/* 459 */     add(o);
/*     */   }
/*     */ 
/*     */   
/*     */   public double popDouble() {
/* 464 */     if (isEmpty()) throw new NoSuchElementException(); 
/* 465 */     return removeDouble(size64() - 1L);
/*     */   }
/*     */ 
/*     */   
/*     */   public double topDouble() {
/* 470 */     if (isEmpty()) throw new NoSuchElementException(); 
/* 471 */     return getDouble(size64() - 1L);
/*     */   }
/*     */ 
/*     */   
/*     */   public double peekDouble(int i) {
/* 476 */     return getDouble(size64() - 1L - i);
/*     */   }
/*     */ 
/*     */ 
/*     */ 
/*     */ 
/*     */ 
/*     */ 
/*     */ 
/*     */ 
/*     */   
/*     */   public boolean rem(double k) {
/* 488 */     long index = indexOf(k);
/* 489 */     if (index == -1L) return false; 
/* 490 */     removeDouble(index);
/* 491 */     return true;
/*     */   }
/*     */ 
/*     */ 
/*     */ 
/*     */ 
/*     */ 
/*     */ 
/*     */ 
/*     */   
/*     */   public boolean addAll(long index, DoubleCollection c) {
/* 502 */     return addAll(index, c);
/*     */   }
/*     */ 
/*     */ 
/*     */ 
/*     */ 
/*     */ 
/*     */ 
/*     */ 
/*     */   
/*     */   public boolean addAll(DoubleCollection c) {
/* 513 */     return addAll(size64(), c);
/*     */   }
/*     */ 
/*     */ 
/*     */ 
/*     */ 
/*     */ 
/*     */ 
/*     */ 
/*     */   
/*     */   @Deprecated
/*     */   public void add(long index, Double ok) {
/* 525 */     add(index, ok.doubleValue());
/*     */   }
/*     */ 
/*     */ 
/*     */ 
/*     */ 
/*     */ 
/*     */ 
/*     */ 
/*     */   
/*     */   @Deprecated
/*     */   public Double set(long index, Double ok) {
/* 537 */     return Double.valueOf(set(index, ok.doubleValue()));
/*     */   }
/*     */ 
/*     */ 
/*     */ 
/*     */ 
/*     */ 
/*     */ 
/*     */ 
/*     */   
/*     */   @Deprecated
/*     */   public Double get(long index) {
/* 549 */     return Double.valueOf(getDouble(index));
/*     */   }
/*     */ 
/*     */ 
/*     */ 
/*     */ 
/*     */ 
/*     */ 
/*     */ 
/*     */   
/*     */   @Deprecated
/*     */   public long indexOf(Object ok) {
/* 561 */     return indexOf(((Double)ok).doubleValue());
/*     */   }
/*     */ 
/*     */ 
/*     */ 
/*     */ 
/*     */ 
/*     */ 
/*     */ 
/*     */   
/*     */   @Deprecated
/*     */   public long lastIndexOf(Object ok) {
/* 573 */     return lastIndexOf(((Double)ok).doubleValue());
/*     */   }
/*     */ 
/*     */ 
/*     */ 
/*     */ 
/*     */ 
/*     */ 
/*     */ 
/*     */   
/*     */   @Deprecated
/*     */   public Double remove(long index) {
/* 585 */     return Double.valueOf(removeDouble(index));
/*     */   }
/*     */ 
/*     */ 
/*     */ 
/*     */ 
/*     */ 
/*     */ 
/*     */ 
/*     */   
/*     */   @Deprecated
/*     */   public void push(Double o) {
/* 597 */     push(o.doubleValue());
/*     */   }
/*     */ 
/*     */ 
/*     */ 
/*     */ 
/*     */ 
/*     */ 
/*     */ 
/*     */   
/*     */   @Deprecated
/*     */   public Double pop() {
/* 609 */     return Double.valueOf(popDouble());
/*     */   }
/*     */ 
/*     */ 
/*     */ 
/*     */ 
/*     */ 
/*     */ 
/*     */ 
/*     */   
/*     */   @Deprecated
/*     */   public Double top() {
/* 621 */     return Double.valueOf(topDouble());
/*     */   }
/*     */ 
/*     */ 
/*     */ 
/*     */ 
/*     */ 
/*     */ 
/*     */ 
/*     */   
/*     */   @Deprecated
/*     */   public Double peek(int i) {
/* 633 */     return Double.valueOf(peekDouble(i));
/*     */   }
/*     */ 
/*     */   
/*     */   public String toString() {
/* 638 */     StringBuilder s = new StringBuilder();
/* 639 */     DoubleIterator i = iterator();
/* 640 */     long n = size64();
/*     */     
/* 642 */     boolean first = true;
/* 643 */     s.append("[");
/* 644 */     while (n-- != 0L) {
/* 645 */       if (first) { first = false; }
/* 646 */       else { s.append(", "); }
/* 647 */        double k = i.nextDouble();
/* 648 */       s.append(String.valueOf(k));
/*     */     } 
/* 650 */     s.append("]");
/* 651 */     return s.toString();
/*     */   }
/*     */ 
/*     */   
/*     */   public static class DoubleSubList
/*     */     extends AbstractDoubleBigList
/*     */     implements Serializable
/*     */   {
/*     */     private static final long serialVersionUID = -7046029254386353129L;
/*     */     protected final DoubleBigList l;
/*     */     protected final long from;
/*     */     protected long to;
/*     */     
/*     */     public DoubleSubList(DoubleBigList l, long from, long to) {
/* 665 */       this.l = l;
/* 666 */       this.from = from;
/* 667 */       this.to = to;
/*     */     }
/*     */     
/*     */     private boolean assertRange() {
/* 671 */       assert this.from <= this.l.size64();
/* 672 */       assert this.to <= this.l.size64();
/* 673 */       assert this.to >= this.from;
/* 674 */       return true;
/*     */     }
/*     */ 
/*     */     
/*     */     public boolean add(double k) {
/* 679 */       this.l.add(this.to, k);
/* 680 */       this.to++;
/* 681 */       assert assertRange();
/* 682 */       return true;
/*     */     }
/*     */ 
/*     */     
/*     */     public void add(long index, double k) {
/* 687 */       ensureIndex(index);
/* 688 */       this.l.add(this.from + index, k);
/* 689 */       this.to++;
/* 690 */       assert assertRange();
/*     */     }
/*     */ 
/*     */     
/*     */     public boolean addAll(long index, Collection<? extends Double> c) {
/* 695 */       ensureIndex(index);
/* 696 */       this.to += c.size();
/* 697 */       return this.l.addAll(this.from + index, c);
/*     */     }
/*     */ 
/*     */     
/*     */     public double getDouble(long index) {
/* 702 */       ensureRestrictedIndex(index);
/* 703 */       return this.l.getDouble(this.from + index);
/*     */     }
/*     */ 
/*     */     
/*     */     public double removeDouble(long index) {
/* 708 */       ensureRestrictedIndex(index);
/* 709 */       this.to--;
/* 710 */       return this.l.removeDouble(this.from + index);
/*     */     }
/*     */ 
/*     */     
/*     */     public double set(long index, double k) {
/* 715 */       ensureRestrictedIndex(index);
/* 716 */       return this.l.set(this.from + index, k);
/*     */     }
/*     */ 
/*     */     
/*     */     public long size64() {
/* 721 */       return this.to - this.from;
/*     */     }
/*     */ 
/*     */     
/*     */     public void getElements(long from, double[][] a, long offset, long length) {
/* 726 */       ensureIndex(from);
/* 727 */       if (from + length > size64()) throw new IndexOutOfBoundsException("End index (" + from + length + ") is greater than list size (" + size64() + ")"); 
/* 728 */       this.l.getElements(this.from + from, a, offset, length);
/*     */     }
/*     */ 
/*     */     
/*     */     public void removeElements(long from, long to) {
/* 733 */       ensureIndex(from);
/* 734 */       ensureIndex(to);
/* 735 */       this.l.removeElements(this.from + from, this.from + to);
/* 736 */       this.to -= to - from;
/* 737 */       assert assertRange();
/*     */     }
/*     */ 
/*     */     
/*     */     public void addElements(long index, double[][] a, long offset, long length) {
/* 742 */       ensureIndex(index);
/* 743 */       this.l.addElements(this.from + index, a, offset, length);
/* 744 */       this.to += length;
/* 745 */       assert assertRange();
/*     */     }
/*     */ 
/*     */ 
/*     */     
/*     */     private final class RandomAccessIter
/*     */       extends DoubleBigListIterators.AbstractIndexBasedBigListIterator
/*     */     {
/*     */       RandomAccessIter(long pos) {
/* 754 */         super(0L, pos);
/*     */       }
/*     */ 
/*     */       
/*     */       protected final double get(long i) {
/* 759 */         return AbstractDoubleBigList.DoubleSubList.this.l.getDouble(AbstractDoubleBigList.DoubleSubList.this.from + i);
/*     */       }
/*     */ 
/*     */ 
/*     */       
/*     */       protected final void add(long i, double k) {
/* 765 */         AbstractDoubleBigList.DoubleSubList.this.add(i, k);
/*     */       }
/*     */ 
/*     */       
/*     */       protected final void set(long i, double k) {
/* 770 */         AbstractDoubleBigList.DoubleSubList.this.set(i, k);
/*     */       }
/*     */ 
/*     */       
/*     */       protected final void remove(long i) {
/* 775 */         AbstractDoubleBigList.DoubleSubList.this.removeDouble(i);
/*     */       }
/*     */ 
/*     */       
/*     */       protected final long getMaxPos() {
/* 780 */         return AbstractDoubleBigList.DoubleSubList.this.to - AbstractDoubleBigList.DoubleSubList.this.from;
/*     */       }
/*     */ 
/*     */       
/*     */       public void add(double k) {
/* 785 */         super.add(k);
/* 786 */         assert AbstractDoubleBigList.DoubleSubList.this.assertRange();
/*     */       }
/*     */ 
/*     */       
/*     */       public void remove() {
/* 791 */         super.remove();
/* 792 */         assert AbstractDoubleBigList.DoubleSubList.this.assertRange();
/*     */       }
/*     */     }
/*     */     
/*     */     private class ParentWrappingIter implements DoubleBigListIterator {
/*     */       private DoubleBigListIterator parent;
/*     */       
/*     */       ParentWrappingIter(DoubleBigListIterator parent) {
/* 800 */         this.parent = parent;
/*     */       }
/*     */ 
/*     */       
/*     */       public long nextIndex() {
/* 805 */         return this.parent.nextIndex() - AbstractDoubleBigList.DoubleSubList.this.from;
/*     */       }
/*     */ 
/*     */       
/*     */       public long previousIndex() {
/* 810 */         return this.parent.previousIndex() - AbstractDoubleBigList.DoubleSubList.this.from;
/*     */       }
/*     */ 
/*     */       
/*     */       public boolean hasNext() {
/* 815 */         return (this.parent.nextIndex() < AbstractDoubleBigList.DoubleSubList.this.to);
/*     */       }
/*     */ 
/*     */       
/*     */       public boolean hasPrevious() {
/* 820 */         return (this.parent.previousIndex() >= AbstractDoubleBigList.DoubleSubList.this.from);
/*     */       }
/*     */ 
/*     */       
/*     */       public double nextDouble() {
/* 825 */         if (!hasNext()) throw new NoSuchElementException(); 
/* 826 */         return this.parent.nextDouble();
/*     */       }
/*     */ 
/*     */       
/*     */       public double previousDouble() {
/* 831 */         if (!hasPrevious()) throw new NoSuchElementException(); 
/* 832 */         return this.parent.previousDouble();
/*     */       }
/*     */ 
/*     */       
/*     */       public void add(double k) {
/* 837 */         this.parent.add(k);
/*     */       }
/*     */ 
/*     */       
/*     */       public void set(double k) {
/* 842 */         this.parent.set(k);
/*     */       }
/*     */ 
/*     */       
/*     */       public void remove() {
/* 847 */         this.parent.remove();
/*     */       }
/*     */ 
/*     */       
/*     */       public long back(long n) {
/* 852 */         if (n < 0L) throw new IllegalArgumentException("Argument must be nonnegative: " + n); 
/* 853 */         long currentPos = this.parent.previousIndex();
/* 854 */         long parentNewPos = currentPos - n;
/*     */ 
/*     */ 
/*     */         
/* 858 */         if (parentNewPos < AbstractDoubleBigList.DoubleSubList.this.from - 1L) parentNewPos = AbstractDoubleBigList.DoubleSubList.this.from - 1L; 
/* 859 */         long toSkip = parentNewPos - currentPos;
/* 860 */         return this.parent.back(toSkip);
/*     */       }
/*     */ 
/*     */       
/*     */       public long skip(long n) {
/* 865 */         if (n < 0L) throw new IllegalArgumentException("Argument must be nonnegative: " + n); 
/* 866 */         long currentPos = this.parent.nextIndex();
/* 867 */         long parentNewPos = currentPos + n;
/* 868 */         if (parentNewPos > AbstractDoubleBigList.DoubleSubList.this.to) parentNewPos = AbstractDoubleBigList.DoubleSubList.this.to; 
/* 869 */         long toSkip = parentNewPos - currentPos;
/* 870 */         return this.parent.skip(toSkip);
/*     */       }
/*     */     }
/*     */ 
/*     */     
/*     */     public DoubleBigListIterator listIterator(long index) {
/* 876 */       ensureIndex(index);
/*     */ 
/*     */ 
/*     */ 
/*     */       
/* 881 */       return (this.l instanceof RandomAccess) ? new RandomAccessIter(index) : new ParentWrappingIter(this.l.listIterator(index + this.from));
/*     */     }
/*     */ 
/*     */     
/*     */     public DoubleSpliterator spliterator() {
/* 886 */       return (this.l instanceof RandomAccess) ? new AbstractDoubleBigList.IndexBasedSpliterator(this.l, this.from, this.to) : super.spliterator();
/*     */     }
/*     */ 
/*     */     
/*     */     public DoubleBigList subList(long from, long to) {
/* 891 */       ensureIndex(from);
/* 892 */       ensureIndex(to);
/* 893 */       if (from > to) throw new IllegalArgumentException("Start index (" + from + ") is greater than end index (" + to + ")");
/*     */ 
/*     */       
/* 896 */       return new DoubleSubList(this, from, to);
/*     */     }
/*     */ 
/*     */     
/*     */     public boolean rem(double k) {
/* 901 */       long index = indexOf(k);
/* 902 */       if (index == -1L) return false; 
/* 903 */       this.to--;
/* 904 */       this.l.removeDouble(this.from + index);
/* 905 */       assert assertRange();
/* 906 */       return true;
/*     */     }
/*     */ 
/*     */     
/*     */     public boolean addAll(long index, DoubleCollection c) {
/* 911 */       return super.addAll(index, c);
/*     */     }
/*     */ 
/*     */     
/*     */     public boolean addAll(long index, DoubleBigList l) {
/* 916 */       return super.addAll(index, l);
/*     */     }
/*     */   }
/*     */   
/*     */   public static class DoubleRandomAccessSubList extends DoubleSubList implements RandomAccess {
/*     */     private static final long serialVersionUID = -107070782945191929L;
/*     */     
/*     */     public DoubleRandomAccessSubList(DoubleBigList l, long from, long to) {
/* 924 */       super(l, from, to);
/*     */     }
/*     */ 
/*     */     
/*     */     public DoubleBigList subList(long from, long to) {
/* 929 */       ensureIndex(from);
/* 930 */       ensureIndex(to);
/* 931 */       if (from > to) throw new IllegalArgumentException("Start index (" + from + ") is greater than end index (" + to + ")");
/*     */ 
/*     */       
/* 934 */       return new DoubleRandomAccessSubList(this, from, to);
/*     */     }
/*     */   }
/*     */ }


/* Location:              C:\Users\ranor\AppData\Roaming\Hytale\install\release\package\game\latest\Server\HytaleServer.jar!\i\\unimi\dsi\fastutil\doubles\AbstractDoubleBigList.class
 * Java compiler version: 8 (52.0)
 * JD-Core Version:       1.1.3
 */